wsppchem/Template.csv
wsppchem/__init__.py
wsppchem/wspp_functions.py
wsppchem/model_and_scaler/LGBM_model.pkl
wsppchem/model_and_scaler/LGBM_scaler.pkl
wsppchem-1.0.dist-info/LICENSE
wsppchem-1.0.dist-info/METADATA
wsppchem-1.0.dist-info/WHEEL
wsppchem-1.0.dist-info/top_level.txt
wsppchem-1.0.dist-info/RECORD
