Metadata-Version: 2.1
Name: wsppchem
Version: 1.0
Summary: Water Solubility Prediction Project
Home-page: https://github.com/Nohalyan/WSPP_Projectppchem
Author: Cossard Lucas and Enzo Venancio
Author-email: lucas.cossard@epfl.ch and enzo.venancio@epfl.ch
Classifier: Programming Language :: Python :: 3
Classifier: License :: OSI Approved :: MIT License
Classifier: Operating System :: OS Independent
Requires-Python: >=3.8
License-File: LICENSE
Requires-Dist: pandas
Requires-Dist: numpy
Requires-Dist: rdkit
Requires-Dist: tqdm
Requires-Dist: lightgbm
Requires-Dist: requests
